gammaspotter/__init__.py
gammaspotter/catalogs/__init__.py
gammaspotter/catalogs/gamma-energies-common.csv
gammaspotter/catalogs/gamma-energies.csv
gammaspotter/fit_models.py
gammaspotter/gui.py
gammaspotter/match_features.py
gammaspotter/process_data.py
gammaspotter-0.2.4.dist-info/entry_points.txt
gammaspotter-0.2.4.dist-info/LICENSE
gammaspotter-0.2.4.dist-info/METADATA
gammaspotter-0.2.4.dist-info/WHEEL
gammaspotter-0.2.4.dist-info/RECORD
