Metadata-Version: 2.1
Name: gammaspotter
Version: 0.2.4
Summary: GUI for detecting and identifying gamma sources.
Home-page: https://github.com/tijnsc/gammaspotter/
License: GPL-3.0-or-later
Author: Tijn Schuitevoerder
Author-email: tijnschuitevoerder@gmail.com
Requires-Python: >=3.10,<3.13
Classifier: License :: OSI Approved :: GNU General Public License v3 or later (GPLv3+)
Classifier: Programming Language :: Python :: 3
Classifier: Programming Language :: Python :: 3.10
Classifier: Programming Language :: Python :: 3.11
Requires-Dist: numpy (>=1.26.2,<2.0.0)
Requires-Dist: pandas (>=2.1.3,<3.0.0)
Requires-Dist: pathlib (>=1.0.1,<2.0.0)
Requires-Dist: pyqtgraph (>=0.13.3,<0.14.0)
Requires-Dist: pyside6 (>=6.6.1,<7.0.0)
Requires-Dist: scipy (>=1.11.4,<2.0.0)
Requires-Dist: tabulate (>=0.9.0,<0.10.0)
Project-URL: Documentation, https://tijnsc.github.io/gammaspotter/
Project-URL: Repository, https://github.com/tijnsc/gammaspotter/
